ssalib/__init__.py
ssalib/error.py
ssalib/montecarlo_ssa.py
ssalib/plotting.py
ssalib/ssa.py
ssalib/svd.py
ssalib/datasets/TF_DEATHS.txt
ssalib/datasets/__init__.py
ssalib/datasets/data_loader.py
ssalib/datasets/oisst2.1_world_60s-60n_sst_monthly.json
ssalib/math_ext/__init__.py
ssalib/math_ext/ar_modeling.py
ssalib/math_ext/matrix_operations.py
ssalib-0.1.3.dist-info/licenses/LICENSE
ssalib-0.1.3.dist-info/METADATA
ssalib-0.1.3.dist-info/WHEEL
ssalib-0.1.3.dist-info/top_level.txt
ssalib-0.1.3.dist-info/RECORD
