Metadata-Version: 2.4
Name: ssalib
Version: 0.1.3
Summary: Singular Spectrum Analysis Library (SSALib)
Home-page: https://github.com/ADSCIAN/ssalib
Author: Alice Alonso, Olivier de Viron, Marnik Vanclooster, Niko Speybroeck
Author-email: Damien Delforge <damien.delforge@adscian.be>
License: BSD-3-Clause
Project-URL: homepage, https://github.com/ADSCIAN/ssalib
Keywords: singular spectrum analysis,time series,decomposition
Classifier: Development Status :: 5 - Production/Stable
Classifier: Intended Audience :: Science/Research
Classifier: License :: OSI Approved :: BSD License
Classifier: Programming Language :: Python :: 3
Classifier: Programming Language :: Python :: 3.9
Classifier: Programming Language :: Python :: 3.10
Classifier: Programming Language :: Python :: 3.11
Classifier: Programming Language :: Python :: 3.12
Classifier: Programming Language :: Python :: 3.13
Classifier: Topic :: Scientific/Engineering
Requires-Python: >=3.9
License-File: LICENSE
Requires-Dist: joblib
Requires-Dist: numpy
Requires-Dist: matplotlib
Requires-Dist: pandas
Requires-Dist: scipy<1.16.0
Requires-Dist: scikit-learn
Requires-Dist: statsmodels
Provides-Extra: test
Requires-Dist: pytest; extra == "test"
Requires-Dist: pytest-cov; extra == "test"
Provides-Extra: dev
Requires-Dist: pytest; extra == "dev"
Requires-Dist: pytest-cov; extra == "dev"
Requires-Dist: black; extra == "dev"
Requires-Dist: flake8; extra == "dev"
Dynamic: home-page
Dynamic: license-file
Dynamic: requires-python
